ngiab_eval/__init__.py
ngiab_eval/__main__.py
ngiab_eval/core.py
ngiab_eval/gage_to_feature_id.py
ngiab_eval/logging_config.py
ngiab_eval/output_formatter.py
ngiab_eval-0.1.6.dist-info/METADATA
ngiab_eval-0.1.6.dist-info/WHEEL
ngiab_eval-0.1.6.dist-info/top_level.txt
ngiab_eval-0.1.6.dist-info/RECORD
