Metadata-Version: 2.4
Name: ngiab_eval
Version: 0.1.6
Summary: Basic KGE and NSE evaluation for the NGIAB project
Author-email: Josh Cunningham <jcunningham8@ua.edu>
Project-URL: Homepage, https://github.com/JoshCu/ngiab_eval
Project-URL: Issues, https://github.com/JoshCu/ngiab_eval/issues
Classifier: Programming Language :: Python :: 3
Classifier: License :: OSI Approved :: MIT License
Classifier: Operating System :: OS Independent
Requires-Python: >=3.9
Requires-Dist: xarray==2024.2.0
Requires-Dist: dask==2024.4.1
Requires-Dist: dask[distributed]==2024.4.1
Requires-Dist: s3fs==2024.3.1
Requires-Dist: zarr==2.17.1
Requires-Dist: hydrotools-nwis-client>=4.1.0
Requires-Dist: hydroeval
Requires-Dist: netcdf4
Requires-Dist: colorama
Provides-Extra: plot
Requires-Dist: seaborn; extra == "plot"
Requires-Dist: matplotlib; extra == "plot"
